XBRLi_converter.py
XBRLi_converter-1.4.dist-info/LICENSE
XBRLi_converter-1.4.dist-info/METADATA
XBRLi_converter-1.4.dist-info/WHEEL
XBRLi_converter-1.4.dist-info/dependency_links.txt
XBRLi_converter-1.4.dist-info/top_level.txt
XBRLi_converter-1.4.dist-info/RECORD
