Metadata-Version: 2.1
Name: XBRLi-converter
Version: 1.4
Summary: Convert XBRLi documents into simple XBRL
Home-page: https://github.com/filippo-ciceri/XBRLI_converter
Author: Filippo Ciceri
Author-email: filippo.ciceri@gmail.com
License: UNKNOWN
Platform: UNKNOWN
Classifier: Programming Language :: Python :: 3
Classifier: License :: OSI Approved :: MIT License
Classifier: Operating System :: OS Independent
License-File: LICENSE
Requires-Dist: bs4
Requires-Dist: lxml
